automemo/__init__.py
automemo/__main__.py
automemo/archiver.py
automemo/asr_service.py
automemo/config.py
automemo/db.py
automemo/logging_config.py
automemo/pipeline.py
automemo/summarizer.py
automemo/utils.py
automemo/watcher.py
recallia-0.0.2.dist-info/METADATA
recallia-0.0.2.dist-info/WHEEL
recallia-0.0.2.dist-info/top_level.txt
recallia-0.0.2.dist-info/RECORD
