Metadata-Version: 2.4
Name: recallia
Version: 0.0.2
Summary: Add your description here
Requires-Python: >=3.12
Requires-Dist: edge-tts>=7.2.7
Requires-Dist: funasr>=1.2.7
Requires-Dist: modelscope>=1.33.0
Requires-Dist: ollama>=0.6.1
Requires-Dist: pydub>=0.25.1
Requires-Dist: rich>=14.2.0
Requires-Dist: structlog>=24.4.0
Requires-Dist: torch>=2.9.1
Requires-Dist: torchaudio>=2.9.1
Requires-Dist: typer>=0.20.0
Requires-Dist: watchdog>=6.0.0
